aliyunsdkr_kvstore/__init__.py
aliyunsdkr_kvstore/endpoint.py
aliyunsdkr_kvstore/request/__init__.py
aliyunsdkr_kvstore/request/v20150101/AddShardingNodeRequest.py
aliyunsdkr_kvstore/request/v20150101/AllocateDirectConnectionRequest.py
aliyunsdkr_kvstore/request/v20150101/AllocateInstancePublicConnectionRequest.py
aliyunsdkr_kvstore/request/v20150101/CancelActiveOperationTasksRequest.py
aliyunsdkr_kvstore/request/v20150101/CheckCloudResourceAuthorizedRequest.py
aliyunsdkr_kvstore/request/v20150101/CreateAccountRequest.py
aliyunsdkr_kvstore/request/v20150101/CreateBackupRequest.py
aliyunsdkr_kvstore/request/v20150101/CreateCacheAnalysisTaskRequest.py
aliyunsdkr_kvstore/request/v20150101/CreateGlobalDistributeCacheRequest.py
aliyunsdkr_kvstore/request/v20150101/CreateGlobalSecurityIPGroupRequest.py
aliyunsdkr_kvstore/request/v20150101/CreateInstanceRequest.py
aliyunsdkr_kvstore/request/v20150101/CreateInstancesRequest.py
aliyunsdkr_kvstore/request/v20150101/CreateParameterGroupRequest.py
aliyunsdkr_kvstore/request/v20150101/CreateTCInstanceRequest.py
aliyunsdkr_kvstore/request/v20150101/CreateTairInstanceRequest.py
aliyunsdkr_kvstore/request/v20150101/CreateTairKVCacheVNodeRequest.py
aliyunsdkr_kvstore/request/v20150101/DeleteAccountRequest.py
aliyunsdkr_kvstore/request/v20150101/DeleteBackupRequest.py
aliyunsdkr_kvstore/request/v20150101/DeleteGlobalSecurityIPGroupRequest.py
aliyunsdkr_kvstore/request/v20150101/DeleteInstanceRequest.py
aliyunsdkr_kvstore/request/v20150101/DeleteParameterGroupRequest.py
aliyunsdkr_kvstore/request/v20150101/DeleteShardingNodeRequest.py
aliyunsdkr_kvstore/request/v20150101/DescribeAccountsRequest.py
aliyunsdkr_kvstore/request/v20150101/DescribeActiveOperationMaintenanceConfigRequest.py
aliyunsdkr_kvstore/request/v20150101/DescribeActiveOperationTaskCountRequest.py
aliyunsdkr_kvstore/request/v20150101/DescribeActiveOperationTaskRequest.py
aliyunsdkr_kvstore/request/v20150101/DescribeActiveOperationTasksRequest.py
aliyun_python_sdk_r_kvstore-2.20.17.dist-info/LICENSE
aliyun_python_sdk_r_kvstore-2.20.17.dist-info/METADATA
aliyun_python_sdk_r_kvstore-2.20.17.dist-info/WHEEL
aliyun_python_sdk_r_kvstore-2.20.17.dist-info/top_level.txt
aliyun_python_sdk_r_kvstore-2.20.17.dist-info/RECORD
